Login/__init__.py
Login/app.py
Login/settings.py
Login/tests/__init__.py
Login/tests/mocks.py
Login/tests/test_login.py
WebMonitoring/ResourceManager.py
WebMonitoring/WebsiteManager.py
WebMonitoring/__init__.py
WebMonitoring/API/__init__.py
WebMonitoring/API/app.py
WebMonitoring/API/constants.py
WebMonitoring/API/settings.py
WebMonitoring/API/add/__init__.py
WebMonitoring/API/add/add_resource.py
WebMonitoring/API/add/add_website.py
WebMonitoring/API/delete/__init__.py
WebMonitoring/API/delete/delete_resource.py
WebMonitoring/API/delete/delete_website.py
WebMonitoring/API/resources/__init__.py
WebMonitoring/API/resources/efficiency_metrics.py
WebMonitoring/API/resources/helpers.py
WebMonitoring/API/resources/last_seven_entries_metrics.py
WebMonitoring/API/resources/metrics_renderer.py
WebMonitoring/API/resources/numerical_helpers.py
WebMonitoring/API/resources/samples_size_resource.py
WebMonitoring/API/resources/samples_time_resource.py
WebMonitoring/API/resources/size_metrics.py
WebMonitoring/API/resources/time_metrics.py
WebMonitoring/API/websites/__init__.py
WebMonitoring/API/websites/samples_size_websites.py
WebMonitoring/API/websites/samples_time_websites.py
WebMonitoring/WebsiteMonitorHelpers/__init__.py
WebMonitoring/WebsiteMonitorHelpers/request_helpers.py
WebMonitoring/WebsiteMonitorHelpers/speedprofile.py
WebMonitoring/clients/SpeedprofileClient.py
WebMonitoring/clients/__init__.py
WebMonitoring/configs/__init__.py
WebMonitoring/configs/constants.py
WebMonitoring/configs/settings.py
WebMonitoring/monitors/ResourceMonitor.py
WebMonitoring/monitors/WebsiteMonitor.py
WebMonitoring/monitors/__init__.py
docker_config/__init__.py
docker_config/generators/__init__.py
docker_config/generators/no_constraint_compose.py
docker_config/generators/tests/__init__.py
docker_config/generators/tests/mocks.py
docker_config/generators/tests/test_no_constraint_compose.py
mysql_config/__init__.py
mysql_config/generate_init_sql.py
mysql_config/settings.py
rafmetrics-0.0.3.dist-info/LICENSE
rafmetrics-0.0.3.dist-info/METADATA
rafmetrics-0.0.3.dist-info/WHEEL
rafmetrics-0.0.3.dist-info/top_level.txt
rafmetrics-0.0.3.dist-info/RECORD
