Metadata-Version: 2.1
Name: rafmetrics
Version: 0.0.3
Summary: Metrics for evaluating the performance and complexity of computer programs
Home-page: UNKNOWN
Author: Rares Folea
License: UNKNOWN
Platform: UNKNOWN
Classifier: Programming Language :: Python :: 3
Classifier: License :: OSI Approved :: MIT License
Classifier: Operating System :: OS Independent
Requires-Python: >=3.6
Requires-Dist: Flask (==1.1.2)
Requires-Dist: Werkzeug (==1.0.1)
Requires-Dist: PyMySQL (==0.9.3)
Requires-Dist: requests (==2.24.0)
Requires-Dist: arrow (==0.16.0)
Requires-Dist: browsermob-proxy (==0.8.0)
Requires-Dist: Flask-Bcrypt (==0.7.1)
Requires-Dist: flask-cors (==3.0.8)
Requires-Dist: selenium (==3.141.0)
Requires-Dist: xvfbwrapper (==0.2.9)
Requires-Dist: flask-mysql (==1.5.1)
Requires-Dist: pytest-mock (==3.3.1)
Requires-Dist: mock (==4.0.2)
Requires-Dist: mysql-connector-python (==8.0.19)
Requires-Dist: simplejson (==3.17.2)
Requires-Dist: flask-shell-ipython (==0.4.1)
Requires-Dist: numpy (==1.19.5)
Requires-Dist: matplotlib (==3.3.1)
Requires-Dist: PyYAML (==5.3.1)
Requires-Dist: scikit-learn (==0.24.1)
